xllify/__init__.py
xllify/__main__.py
xllify/diagnostics.py
xllify/funcinfo.py
xllify/install.py
xllify/py.typed
xllify/rpc_server.py
xllify/rtd_client.py
xllify_xllify-0.7.7.dist-info/licenses/LICENSE
xllify_xllify-0.7.7.dist-info/METADATA
xllify_xllify-0.7.7.dist-info/WHEEL
xllify_xllify-0.7.7.dist-info/entry_points.txt
xllify_xllify-0.7.7.dist-info/top_level.txt
xllify_xllify-0.7.7.dist-info/RECORD
