Metadata-Version: 2.4
Name: xllify_xllify
Version: 0.7.7
Summary: Python SDK for creating Excel XLL add-ins with xllify
Author: Alex Reid
License: MIT
Project-URL: Homepage, https://xllify.com
Project-URL: Documentation, https://xllify.com
Project-URL: Repository, https://github.com/xllifycom/xllify-python
Project-URL: Issues, https://github.com/xllifycom/xllify-python/issues
Keywords: excel,xll,udf,add-in,finance
Classifier: Development Status :: 3 - Alpha
Classifier: Intended Audience :: Developers
Classifier: License :: OSI Approved :: MIT License
Classifier: Operating System :: Microsoft :: Windows
Classifier: Programming Language :: Python :: 3.10
Classifier: Programming Language :: Python :: 3.11
Classifier: Programming Language :: Python :: 3.12
Classifier: Topic :: Office/Business :: Financial :: Spreadsheet
Requires-Python: >=3.8
License-File: LICENSE
Requires-Dist: pyzmq>=25.0
Provides-Extra: dev
Requires-Dist: pytest>=7.0; extra == "dev"
Requires-Dist: pytest-cov>=4.0; extra == "dev"
Requires-Dist: black>=23.0; extra == "dev"
Dynamic: license-file
